rmp/__init__.py
rmp/application.py
rmp/backend.py
rmp/domain.py
rmp/flow_metrics.py
rmp/jira.py
rmp/py.typed
rmp/sql_model.py
rmp-0.0.1.dist-info/LICENSE
rmp-0.0.1.dist-info/METADATA
rmp-0.0.1.dist-info/WHEEL
rmp-0.0.1.dist-info/RECORD
