Metadata-Version: 2.3
Name: rmp
Version: 0.0.1
Summary: Analyze team performance for better predictability
License: MIT
Author: Ergo Sarapu
Requires-Python: >=3.11,<4.0
Classifier: License :: OSI Approved :: MIT License
Classifier: Programming Language :: Python :: 3
Classifier: Programming Language :: Python :: 3.11
Classifier: Programming Language :: Python :: 3.12
Classifier: Programming Language :: Python :: 3.13
Requires-Dist: datetimerange (>=2.3.1,<3.0.0)
Requires-Dist: eventsourcing (>=9.3.5,<10.0.0)
Requires-Dist: eventsourcing-sqlalchemy (>=0.10,<0.11)
Requires-Dist: pandas (>=2.2.2,<3.0.0)
Requires-Dist: pytz (>=2025.1,<2026.0)
Requires-Dist: requests (>=2.32.3,<3.0.0)
Requires-Dist: sqlalchemy (>=2.0.37,<3.0.0)
Requires-Dist: tqdm (>=4.66.6,<5.0.0)
Requires-Dist: typing-extensions (>=4.13.0,<5.0.0)
